odoo/addons/base_export_async/README.rst
odoo/addons/base_export_async/__init__.py
odoo/addons/base_export_async/__manifest__.py
odoo/addons/base_export_async/data/config_parameter.xml
odoo/addons/base_export_async/data/cron.xml
odoo/addons/base_export_async/data/mail_template.xml
odoo/addons/base_export_async/i18n/base_export_async.pot
odoo/addons/base_export_async/i18n/da.po
odoo/addons/base_export_async/i18n/de.po
odoo/addons/base_export_async/i18n/fr.po
odoo/addons/base_export_async/i18n/it.po
odoo/addons/base_export_async/i18n/pt.po
odoo/addons/base_export_async/i18n/zh_CN.po
odoo/addons/base_export_async/models/__init__.py
odoo/addons/base_export_async/models/delay_export.py
odoo/addons/base_export_async/readme/CONTRIBUTORS.rst
odoo/addons/base_export_async/readme/DESCRIPTION.rst
odoo/addons/base_export_async/readme/USAGE.rst
odoo/addons/base_export_async/security/ir.model.access.csv
odoo/addons/base_export_async/security/ir_rule.xml
odoo/addons/base_export_async/static/description/icon.png
odoo/addons/base_export_async/static/description/index.html
odoo/addons/base_export_async/static/src/js/data_export.js
odoo/addons/base_export_async/static/src/xml/base.xml
odoo/addons/base_export_async/tests/__init__.py
odoo/addons/base_export_async/tests/test_base_export_async.py
odoo/addons/base_export_async/views/assets.xml
odoo14_addon_base_export_async-14.0.1.1.0.dist-info/METADATA
odoo14_addon_base_export_async-14.0.1.1.0.dist-info/WHEEL
odoo14_addon_base_export_async-14.0.1.1.0.dist-info/top_level.txt
odoo14_addon_base_export_async-14.0.1.1.0.dist-info/RECORD
